garcon/__init__.py
garcon/activity.py
garcon/context.py
garcon/decider.py
garcon/event.py
garcon/log.py
garcon/param.py
garcon/runner.py
garcon/task.py
garcon/utils.py
tests/__init__.py
tests/conftest.py
tests/test_activity.py
tests/test_context.py
tests/test_decider.py
tests/test_log.py
tests/test_param.py
tests/test_runner.py
tests/test_task.py
tests/test_utils.py
tests/fixtures/__init__.py
tests/fixtures/decider.py
tests/fixtures/log.py
tests/fixtures/flows/__init__.py
tests/fixtures/flows/example.py
Garcon-1.1.1.dist-info/LICENSE
Garcon-1.1.1.dist-info/METADATA
Garcon-1.1.1.dist-info/WHEEL
Garcon-1.1.1.dist-info/top_level.txt
Garcon-1.1.1.dist-info/RECORD
