Metadata-Version: 2.1
Name: Garcon
Version: 1.1.1
Summary: Lightweight library for AWS SWF.
Home-page: https://github.com/xethorn/garcon/
Author: Michael Ortali
Author-email: hello@xethorn.net
License: MIT
Classifier: Programming Language :: Python :: 3.8
Classifier: Programming Language :: Python :: 3.9
Classifier: Programming Language :: Python :: 3.10
Classifier: Programming Language :: Python :: 3.11
Classifier: Programming Language :: Python :: 3.12
License-File: LICENSE
Requires-Dist: boto3
Requires-Dist: backoff
